folder_structure_generator_7edge/__init__.py
folder_structure_generator_7edge/dredd-template.yml
folder_structure_generator_7edge/generator.py
folder_structure_generator_7edge/hooks-template.py
folder_structure_generator_7edge/serverless-template.yml
folder_structure_generator_7edge/swagger-template.json
folder_structure_generator_7edge/backend_folder/.gitignore
folder_structure_generator_7edge/backend_folder/README.md
folder_structure_generator_7edge/backend_folder/access_token_genation.py
folder_structure_generator_7edge/backend_folder/api-testing.sh
folder_structure_generator_7edge/backend_folder/serverless-compose.yml
folder_structure_generator_7edge/backend_folder/devops/dependencies/node/dependency.tf
folder_structure_generator_7edge/backend_folder/devops/dependencies/node/package.json
folder_structure_generator_7edge/backend_folder/devops/dependencies/node/variables.tf
folder_structure_generator_7edge/backend_folder/devops/dependencies/python/dependency-python.tf
folder_structure_generator_7edge/backend_folder/devops/dependencies/python/requirements.txt
folder_structure_generator_7edge/backend_folder/devops/dependencies/python/requirements2.txt
folder_structure_generator_7edge/backend_folder/devops/dependencies/python/variables.tf
folder_structure_generator_7edge/backend_folder/devops/dependencies/python/extra/_cffi_backend.cpython-310-x86_64-linux-gnu.so
folder_structure_generator_7edge/backend_folder/devops/dependencies/python/extra/_cffi_backend.cpython-38-x86_64-linux-gnu.so
folder_structure_generator_7edge/backend_folder/devops/dependencies/python/extra/cffi/__init__.py
folder_structure_generator_7edge/backend_folder/devops/dependencies/python/extra/cffi/_cffi_errors.h
folder_structure_generator_7edge/backend_folder/devops/dependencies/python/extra/cffi/_cffi_include.h
folder_structure_generator_7edge/backend_folder/devops/dependencies/python/extra/cffi/_embedding.h
folder_creation_test-1.6.1.dist-info/METADATA
folder_creation_test-1.6.1.dist-info/WHEEL
folder_creation_test-1.6.1.dist-info/entry_points.txt
folder_creation_test-1.6.1.dist-info/top_level.txt
folder_structure_generator_7edge/backend_folder/devops/dependencies/python/extra/certifi-2021.10.8.dist-info/INSTALLER
folder_structure_generator_7edge/backend_folder/devops/dependencies/python/extra/certifi-2021.10.8.dist-info/LICENSE
folder_structure_generator_7edge/backend_folder/devops/dependencies/python/extra/certifi-2021.10.8.dist-info/METADATA
folder_structure_generator_7edge/backend_folder/devops/dependencies/python/extra/certifi-2021.10.8.dist-info/RECORD
folder_structure_generator_7edge/backend_folder/devops/dependencies/python/extra/certifi-2021.10.8.dist-info/WHEEL
folder_structure_generator_7edge/backend_folder/devops/dependencies/python/extra/certifi-2021.10.8.dist-info/top_level.txt
folder_structure_generator_7edge/backend_folder/devops/dependencies/python/extra/cffi-1.14.6.dist-info/INSTALLER
folder_structure_generator_7edge/backend_folder/devops/dependencies/python/extra/cffi-1.14.6.dist-info/LICENSE
folder_structure_generator_7edge/backend_folder/devops/dependencies/python/extra/cffi-1.14.6.dist-info/METADATA
folder_structure_generator_7edge/backend_folder/devops/dependencies/python/extra/cffi-1.14.6.dist-info/RECORD
folder_structure_generator_7edge/backend_folder/devops/dependencies/python/extra/cffi-1.14.6.dist-info/WHEEL
folder_structure_generator_7edge/backend_folder/devops/dependencies/python/extra/cffi-1.14.6.dist-info/entry_points.txt
folder_structure_generator_7edge/backend_folder/devops/dependencies/python/extra/cffi-1.14.6.dist-info/top_level.txt
folder_structure_generator_7edge/backend_folder/devops/dependencies/python/extra/cffi-1.16.0.dist-info/INSTALLER
folder_structure_generator_7edge/backend_folder/devops/dependencies/python/extra/cffi-1.16.0.dist-info/LICENSE
folder_structure_generator_7edge/backend_folder/devops/dependencies/python/extra/cffi-1.16.0.dist-info/METADATA
folder_structure_generator_7edge/backend_folder/devops/dependencies/python/extra/cffi-1.16.0.dist-info/RECORD
folder_structure_generator_7edge/backend_folder/devops/dependencies/python/extra/cffi-1.16.0.dist-info/WHEEL
folder_structure_generator_7edge/backend_folder/devops/dependencies/python/extra/cffi-1.16.0.dist-info/entry_points.txt
folder_structure_generator_7edge/backend_folder/devops/dependencies/python/extra/cffi-1.16.0.dist-info/top_level.txt
folder_structure_generator_7edge/backend_folder/devops/dependencies/python/extra/cryptography-2.8.dist-info/AUTHORS.rst
folder_structure_generator_7edge/backend_folder/devops/dependencies/python/extra/cryptography-2.8.dist-info/INSTALLER
folder_structure_generator_7edge/backend_folder/devops/dependencies/python/extra/cryptography-2.8.dist-info/LICENSE
folder_structure_generator_7edge/backend_folder/devops/dependencies/python/extra/cryptography-2.8.dist-info/LICENSE.APACHE
folder_structure_generator_7edge/backend_folder/devops/dependencies/python/extra/cryptography-2.8.dist-info/LICENSE.BSD
folder_structure_generator_7edge/backend_folder/devops/dependencies/python/extra/cryptography-2.8.dist-info/LICENSE.PSF
folder_structure_generator_7edge/backend_folder/devops/dependencies/python/extra/cryptography-2.8.dist-info/METADATA
folder_structure_generator_7edge/backend_folder/devops/dependencies/python/extra/cryptography-2.8.dist-info/RECORD
folder_structure_generator_7edge/backend_folder/devops/dependencies/python/extra/cryptography-2.8.dist-info/WHEEL
folder_structure_generator_7edge/backend_folder/devops/dependencies/python/extra/cryptography-2.8.dist-info/top_level.txt
folder_structure_generator_7edge/backend_folder/devops/dependencies/python/extra/cryptography-41.0.5.dist-info/INSTALLER
folder_structure_generator_7edge/backend_folder/devops/dependencies/python/extra/cryptography-41.0.5.dist-info/LICENSE
folder_structure_generator_7edge/backend_folder/devops/dependencies/python/extra/cryptography-41.0.5.dist-info/LICENSE.APACHE
